{
  "version": "7",
  "dialect": "postgresql",
  "entries": [
    {
      "idx": 0,
      "version": "7",
      "when": 1772533242894,
      "tag": "0000_outgoing_night_thrasher",
      "breakpoints": true
    },
    {
      "idx": 1,
      "version": "7",
      "when": 1773229582486,
      "tag": "0001_aspiring_agent_brand",
      "breakpoints": true
    },
    {
      "idx": 2,
      "version": "7",
      "when": 1773230321534,
      "tag": "0002_groovy_romulus",
      "breakpoints": true
    },
    {
      "idx": 3,
      "version": "7",
      "when": 1773705600000,
      "tag": "0003_sturdy_lead_status",
      "breakpoints": true
    },
    {
      "idx": 4,
      "version": "7",
      "when": 1773792000000,
      "tag": "0004_clear_lead_links",
      "breakpoints": true
    },
    {
      "idx": 5,
      "version": "7",
      "when": 1774290621005,
      "tag": "0005_regular_quentin_quire",
      "breakpoints": true
    },
    {
      "idx": 6,
      "version": "7",
      "when": 1774291790448,
      "tag": "0006_nosy_iron_monger",
      "breakpoints": true
    },
    {
      "idx": 7,
      "version": "7",
      "when": 1774298035769,
      "tag": "0007_sweet_marvel_boy",
      "breakpoints": true
    }
  ]
}